{
  "version": 1.1,
  "atDirectives": [
    {
      "name": "@tailwind",
      "description": "Tailwind CSS directive to inject styles",
      "references": [
        {
          "name": "Tailwind CSS Documentation",
          "url": "https://tailwindcss.com/docs/functions-and-directives#tailwind"
        }
      ]
    },
    {
      "name": "@apply",
      "description": "Tailwind CSS directive to apply utility classes",
      "references": [
        {
          "name": "Tailwind CSS Documentation",
          "url": "https://tailwindcss.com/docs/functions-and-directives#apply"
        }
      ]
    },
    {
      "name": "@layer",
      "description": "Tailwind CSS directive to specify layer for custom styles",
      "references": [
        {
          "name": "Tailwind CSS Documentation",
          "url": "https://tailwindcss.com/docs/functions-and-directives#layer"
        }
      ]
    },
    {
      "name": "@responsive",
      "description": "Tailwind CSS directive to generate responsive variants",
      "references": [
        {
          "name": "Tailwind CSS Documentation",
          "url": "https://tailwindcss.com/docs/functions-and-directives#responsive"
        }
      ]
    },
    {
      "name": "@screen",
      "description": "Tailwind CSS directive to create media queries",
      "references": [
        {
          "name": "Tailwind CSS Documentation",
          "url": "https://tailwindcss.com/docs/functions-and-directives#screen"
        }
      ]
    },
    {
      "name": "@variants",
      "description": "Tailwind CSS directive to generate variants",
      "references": [
        {
          "name": "Tailwind CSS Documentation",
          "url": "https://tailwindcss.com/docs/functions-and-directives#variants"
        }
      ]
    }
  ]
}
